Metadata-Version: 1.1
Name: pyramid-httpauth
Version: 1.0.3
Summary: pyramid_httpauth
Home-page: https://github.com/tarzanjw/pyramid_httpauth
Author: Tarzan
Author-email: hoc3010@gmail.com
License: UNKNOWN
Keywords: web pylons pyramid restful auth basic digest
Platform: UNKNOWN
Classifier: Programming Language :: Python :: 2.7
Classifier: Programming Language :: Python :: 3.4
Classifier: Framework :: Pyramid
Classifier: Topic :: Internet :: WWW/HTTP
Classifier: Topic :: Internet :: WWW/HTTP :: WSGI :: Application
